{"portfolio":{"portfolioId":"main","totalValueBase":139932041.67,"dailyPnlBase":-1850000.0,"name":"KR+US 섹터 분산 포트폴리오","baseCurrency":"KRW","benchmark":"ARCA:SPY","riskLimits":{"maxWeightPerName":0.15,"maxVar95":0.03,"maxSectorWeight":0.3,"maxHoldings":15}},"positions":[{"positionId":"main:KRX:105560","portfolioId":"main","instrumentId":"KRX:105560","lastPriceLocal":174000.0,"marketValueBase":17400000.0,"weight":0.124346,"dailyPnlBase":-120000.0,"unrealizedPnlPct":0.022928,"quantity":100,"avgCostLocal":170100.0,"openedAt":"2026-07-03","instrument":{"name":"KB Financial Group","nameKo":"KB금융","ticker":"105560","market":"KRX","sectorId":"FIN","sector":"금융","currency":"KRW"}},{"positionId":"main:KRX:005380","portfolioId":"main","instrumentId":"KRX:005380","lastPriceLocal":455000.0,"marketValueBase":13650000.0,"weight":0.097547,"dailyPnlBase":-810000.0,"unrealizedPnlPct":0.961207,"quantity":30,"avgCostLocal":232000,"openedAt":"2025-06-20","instrument":{"name":"Hyundai Motor","nameKo":"현대차","ticker":"005380","market":"KRX","sectorId":"CD","sector":"경기소비재","currency":"KRW"}},{"positionId":"main:ARCA:SPY","portfolioId":"main","instrumentId":"ARCA:SPY","lastPriceLocal":745.4,"marketValueBase":11464624.7,"weight":0.08193,"dailyPnlBase":0.0,"unrealizedPnlPct":0.427969,"quantity":10,"avgCostLocal":522.0,"openedAt":"2025-01-06","instrument":{"name":"SPDR S&P 500 ETF","nameKo":"SPY","ticker":"SPY","market":"ARCA","sectorId":"BROAD","sector":"시장지수","currency":"USD"}},{"positionId":"main:XNAS:AAPL","portfolioId":"main","instrumentId":"XNAS:AAPL","lastPriceLocal":313.39,"marketValueBase":9640189.79,"weight":0.068892,"dailyPnlBase":0.0,"unrealizedPnlPct":0.680375,"quantity":20,"avgCostLocal":186.5,"openedAt":"2025-02-03","instrument":{"name":"Apple Inc.","nameKo":"애플","ticker":"AAPL","market":"XNAS","sectorId":"IT","sector":"정보기술","currency":"USD"}},{"positionId":"main:KRX:015760","portfolioId":"main","instrumentId":"KRX:015760","lastPriceLocal":36650.0,"marketValueBase":9162500.0,"weight":0.065478,"dailyPnlBase":-237500.0,"unrealizedPnlPct":-0.04183,"quantity":250,"avgCostLocal":38250.0,"openedAt":"2026-07-03","instrument":{"name":"KEPCO","nameKo":"한국전력","ticker":"015760","market":"KRX","sectorId":"UTIL","sector":"유틸리티","currency":"KRW"}},{"positionId":"main:XNAS:QQQ","portfolioId":"main","instrumentId":"XNAS:QQQ","lastPriceLocal":711.44,"marketValueBase":8753842.34,"weight":0.062558,"dailyPnlBase":0.0,"unrealizedPnlPct":0.588036,"quantity":8,"avgCostLocal":448.0,"openedAt":"2025-02-24","instrument":{"name":"Invesco QQQ Trust","nameKo":"QQQ","ticker":"QQQ","market":"XNAS","sectorId":"BROAD","sector":"시장지수","currency":"USD"}},{"positionId":"main:KRX:271560","portfolioId":"main","instrumentId":"KRX:271560","lastPriceLocal":139300.0,"marketValueBase":8358000.0,"weight":0.059729,"dailyPnlBase":-24000.0,"unrealizedPnlPct":0.02201,"quantity":60,"avgCostLocal":136300.0,"openedAt":"2026-07-03","instrument":{"name":"Orion","nameKo":"오리온","ticker":"271560","market":"KRX","sectorId":"CS","sector":"필수소비재","currency":"KRW"}},{"positionId":"main:XNAS:GOOGL","portfolioId":"main","instrumentId":"XNAS:GOOGL","lastPriceLocal":361.92,"marketValueBase":8349765.84,"weight":0.05967,"dailyPnlBase":0.0,"unrealizedPnlPct":1.24795,"quantity":15,"avgCostLocal":161.0,"openedAt":"2025-04-21","instrument":{"name":"Alphabet Inc. (A)","nameKo":"알파벳","ticker":"GOOGL","market":"XNAS","sectorId":"COMM","sector":"커뮤니케이션","currency":"USD"}},{"positionId":"main:KRX:005490","portfolioId":"main","instrumentId":"KRX:005490","lastPriceLocal":308500.0,"marketValueBase":7712500.0,"weight":0.055116,"dailyPnlBase":-175000.0,"unrealizedPnlPct":-0.035937,"quantity":25,"avgCostLocal":320000.0,"openedAt":"2026-07-03","instrument":{"name":"POSCO Holdings","nameKo":"POSCO홀딩스","ticker":"005490","market":"KRX","sectorId":"MAT","sector":"소재","currency":"KRW"}},{"positionId":"main:KRX:035420","portfolioId":"main","instrumentId":"KRX:035420","lastPriceLocal":192300.0,"marketValueBase":7692000.0,"weight":0.05497,"dailyPnlBase":-200000.0,"unrealizedPnlPct":-0.018878,"quantity":40,"avgCostLocal":196000,"openedAt":"2025-02-14","instrument":{"name":"NAVER","nameKo":"네이버","ticker":"035420","market":"KRX","sectorId":"COMM","sector":"커뮤니케이션","currency":"KRW"}},{"positionId":"main:KRX:096770","portfolioId":"main","instrumentId":"KRX:096770","lastPriceLocal":103100.0,"marketValueBase":6186000.0,"weight":0.044207,"dailyPnlBase":-84000.0,"unrealizedPnlPct":0.085263,"quantity":60,"avgCostLocal":95000.0,"openedAt":"2026-07-03","instrument":{"name":"SK Innovation","nameKo":"SK이노베이션","ticker":"096770","market":"KRX","sectorId":"ENE","sector":"에너지","currency":"KRW"}},{"positionId":"main:XNYS:JPM","portfolioId":"main","instrumentId":"XNYS:JPM","lastPriceLocal":330.62,"marketValueBase":6102121.09,"weight":0.043608,"dailyPnlBase":0.0,"unrealizedPnlPct":0.674025,"quantity":12,"avgCostLocal":197.5,"openedAt":"2025-01-27","instrument":{"name":"JPMorgan Chase & Co.","nameKo":"JP모간","ticker":"JPM","market":"XNYS","sectorId":"FIN","sector":"금융","currency":"USD"}},{"positionId":"main:XNYS:JNJ","portfolioId":"main","instrumentId":"XNYS:JNJ","lastPriceLocal":263.4,"marketValueBase":6076835.55,"weight":0.043427,"dailyPnlBase":0.0,"unrealizedPnlPct":0.001369,"quantity":15,"avgCostLocal":263.04,"openedAt":"2026-07-03","instrument":{"name":"Johnson & Johnson","nameKo":"존슨앤드존슨","ticker":"JNJ","market":"XNYS","sectorId":"HC","sector":"헬스케어","currency":"USD"}},{"positionId":"main:XNAS:MSFT","portfolioId":"main","instrumentId":"XNAS:MSFT","lastPriceLocal":383.34,"marketValueBase":5895960.87,"weight":0.042134,"dailyPnlBase":0.0,"unrealizedPnlPct":-0.022092,"quantity":10,"avgCostLocal":392.0,"openedAt":"2025-03-17","instrument":{"name":"Microsoft Corp.","nameKo":"마이크로소프트","ticker":"MSFT","market":"XNAS","sectorId":"IT","sector":"정보기술","currency":"USD"}},{"positionId":"main:KRX:068270","portfolioId":"main","instrumentId":"KRX:068270","lastPriceLocal":177700.0,"marketValueBase":5331000.0,"weight":0.038097,"dailyPnlBase":-147000.0,"unrealizedPnlPct":0.009659,"quantity":30,"avgCostLocal":176000,"openedAt":"2025-07-11","instrument":{"name":"Celltrion","nameKo":"셀트리온","ticker":"068270","market":"KRX","sectorId":"HC","sector":"헬스케어","currency":"KRW"}},{"positionId":"main:XNAS:NVDA","portfolioId":"main","instrumentId":"XNAS:NVDA","lastPriceLocal":204.12,"marketValueBase":4709201.49,"weight":0.033653,"dailyPnlBase":0.0,"unrealizedPnlPct":0.790526,"quantity":15,"avgCostLocal":114.0,"openedAt":"2025-05-27","instrument":{"name":"NVIDIA Corp.","nameKo":"엔비디아","ticker":"NVDA","market":"XNAS","sectorId":"IT","sector":"정보기술","currency":"USD"}},{"positionId":"main:KRX:035720","portfolioId":"main","instrumentId":"KRX:035720","lastPriceLocal":34475.0,"marketValueBase":3447500.0,"weight":0.024637,"dailyPnlBase":-52500.0,"unrealizedPnlPct":-0.274211,"quantity":100,"avgCostLocal":47500,"openedAt":"2025-04-08","instrument":{"name":"Kakao","nameKo":"카카오","ticker":"035720","market":"KRX","sectorId":"COMM","sector":"커뮤니케이션","currency":"KRW"}}]}